tensor4/__init__.py
tensor4/emitters.py
tensor4/generator.py
tensor4/trace_parser.py
tensor4/var_table.py
tensor4-0.0.2.dist-info/DESCRIPTION.rst
tensor4-0.0.2.dist-info/METADATA
tensor4-0.0.2.dist-info/RECORD
tensor4-0.0.2.dist-info/WHEEL
tensor4-0.0.2.dist-info/metadata.json
tensor4-0.0.2.dist-info/top_level.txt
